algebra-de-bool-funciones-logicas/eje2/eje2.v
///Modulo para la operación AND
module eje2(
    input wire A,
    input wire B,
    input wire C,
    output wire X
);
    
    assign X = ~(A | B | C);  // Operación NOR entre A, B Y C
endmodule

algebra-de-bool-funciones-logicas/eje3/eje3_tb.v
/*
 * Testbench para [nombre del módulo]
 *
 * Un testbench es un módulo Verilog que:
 * 1. Genera estímulos (valores de entrada) para el circuito bajo prueba
 * 2. Monitorea las salidas
 * 3. No tiene entradas/salidas reales - es solo para simulación
 */

// --- PARTE FIJA (SIEMPRE USAR) ---
`default_nettype none
// Deshabilita la inferencia automática de tipos de señales para evitar errores comunes.

`timescale 100 ns / 10 ns
// Define la escala de tiempo para la simulación:
// - La unidad de tiempo es 100 ns.
// - La precisión de los retardos es de 10 ns.

module eje2_tb();
// Define el módulo del testbench llamado `eje1_tb`.

parameter DURATION = 100;
// Parámetro que define la duración total de la simulación en unidades de tiempo.

reg reset;
// Señal de tipo `reg` para simular un reset del circuito bajo prueba.

// --- PARTE FIJA (SIEMPRE USAR) ---
// Declaración de señales de entrada (reg) y salida (wire)
reg A;
// Señal de entrada `A` para el módulo bajo prueba.

reg B;
// Señal de entrada `B` para el módulo bajo prueba.

reg C;
// Señal de entrada `C` para el módulo bajo prueba.

wire X;
// Señal de salida `X` del módulo bajo prueba.

integer n;
// Variable entera para usar como índice en el bucle `for`.

reg [18:0] i;
// Registro de 19 bits para almacenar estímulos de entrada para `A`.

reg [18:0] j;
// Registro de 19 bits para almacenar estímulos de entrada para `B`.

reg [18:0] k;
// Registro de 19 bits para almacenar estímulos de entrada para `C`.

// Instanciación del módulo bajo prueba
eje2 UUT (
    .A(A),  // Conecta la señal `A` del testbench al puerto `A` del módulo.
    .B(B),  // Conecta la señal `B` del testbench al puerto `B` del módulo.
    .C(C),  // Conecta la señal `C` del testbench al puerto `C` del módulo.
    .X(X)   // Conecta la señal `X` del módulo al testbench para monitoreo.
    // ...
);

// --- PARTE FIJA (SIEMPRE USAR) ---
initial begin
  $dumpfile("eje2_tb.vcd");
  // Crea un archivo de salida llamado `eje2_tb.vcd` para almacenar la traza de la simulación.

  $dumpvars(0, A, B, C, X);
  // Especifica que se monitorearán todas las variables del módulo `eje1_tb`.

  reset = 1;
  // Activa la señal de reset al inicio de la simulación.

  #1;
  // Espera 1 unidad de tiempo (100 ns en este caso).

  reset = 0;
  // Desactiva la señal de reset.

  // Generar estímulos para las entradas
  i = 19'b0111111000011110000;
  // Asigna un patrón binario de 19 bits a la señal `i` (estímulos para `A`).

  j = 19'b0000111100001111000;
  // Asigna un patrón binario de 19 bits a la señal `j` (estímulos para `B`).

  k = 19'b0010010001000100010;
  // Asigna un patrón binario de 19 bits a la señal `k` (estímulos para `C`).

  for (n = 19; n >= 0; n = n - 1) begin
    // Bucle para recorrer los 9 bits de las señales `i` y `j`.

    A = i[n];
    // Asigna el bit `n` de `i` a la señal `A`.

    B = j[n];
    // Asigna el bit `n` de `j` a la señal `B`.

    C = k[n];

    #1;
    // Espera 1 unidad de tiempo (100 ns) antes de pasar al siguiente bit.
  end

  // Finalizar simulación
  #(DURATION) $display("Fin de la simulación");
  // Espera el tiempo definido por `DURATION` y muestra un mensaje indicando el fin de la simulación.

  $finish;
  // Finaliza la simulación.
end

endmodule
// Fin del módulo del testbench.

algebra-de-bool-funciones-logicas/eje2/eje2_tb.vcd
$date
	Sat May 10 10:03:45 2025
$end
$version
	Icarus Verilog
$end
$timescale
	1ps
$end
$scope module eje2_tb $end
$var reg 1 ! A $end
$upscope $end
$scope module eje2_tb $end
$var reg 1 " B $end
$upscope $end
$scope module eje2_tb $end
$var reg 1 # C $end
$upscope $end
$scope module eje2_tb $end
$var wire 1 $ X $end
$upscope $end
$enddefinitions $end
$comment Show the parameter values. $end
$dumpall
$end
#0
$dumpvars
x$
x#
x"
x!
$end
#200000
1$
0#
0"
0!
#300000
0$
1!
#400000
1#
#500000
0#
#600000
1"
#700000
1#
#800000
0#
#900000
0!
#1000000
1$
0"
#1100000
0$
1#
#1200000
1$
0#
#1300000
0$
1!
#1400000
1"
#1500000
1#
#1600000
0#
#1700000
0!
#1800000
1$
0"
#1900000
0$
1#
#2000000
1$
0#
