circuitos-combinacionales/eje4/eje4_c.v
module eje4_c(
    input [3:0] bits,
    output reg [6:0] Cod_Hamming
    //output [6:0] Cod_Hamming
);

wire p1 = bits[3] ^ bits[2] ^ bits[0];
wire p2 = bits[3] ^ bits[1] ^ bits[0];
wire p3 = bits[2] ^ bits[1] ^ bits[0];

//assign Cod_Hamming = {p1, p2, bits[3], p3, bits[2], bits[1], bits[0]};
 
always @(*) begin
    Cod_Hamming[6] = p1; // Paridad 1
    Cod_Hamming[5] = p2; // Paridad 2
    Cod_Hamming[4] = bits[3]; // Dato 1
    Cod_Hamming[3] = p3; // Paridad 3
    Cod_Hamming[2] = bits[2]; // Dato 2
    Cod_Hamming[1] = bits[1]; // Dato 3
    Cod_Hamming[0] = bits[0]; // Dato 4
    // Cod_Hamming[6:0] = {p1, p2, bits[3], p3, bits[2], bits[1], bits[0]};
end

endmodule

circuitos-combinacionales/eje4/eje4_b_2.v
module eje4_b_2 (
    input [3:0] BN,
    output reg [3:0] G

);


    always @(*) begin
        if( BN <= 4'd15) begin
            // Como pasar de BN->G
            /*
            1 - El bit MSB se mantiene
            2 - De izq a derecha aplicamos suma binaria para cada par adyacente de bits (el acarreo se descarta)
            por ejemplo =  0011 -> 0 se fija, 0+0 = 0, 0+1 = 1, 1+1 = 0 (1 de acarreo descartado)
                        --> 0010
            para esto utilizaremos el operador XOR ( ^ ) que devuelve 1 si son diferentes
            recordar que eun reg de bits
            se ordena asi:
            G[MSB _ _ _ LSB]
            */
            G[3] = BN[3]; //MSB
            G[2] = BN[3] ^ BN[2];
            G[1] = BN[2] ^ BN[1];
            G[0] = BN[1] ^ BN[0];

        end else begin
            G = 4'bxxxx;
        end
    end
endmodule

circuitos-combinacionales/eje4/eje4_b.v
module eje4_b(
input wire E1,
input wire E2,
input wire E3,
input wire E4,
output wire A,
output wire B,
output wire C,
output wire D
);

assign A = (E1 & ~E2 & ~E3 & ~E4) | (E1 & ~E2 & ~E3 & E4) | (E1 & ~E2 & E3 & ~E4) | (E1 & ~E2 & E3 & E4) |
           (E1 & E2 & ~E3 & ~E4) | (E1 & E2 & ~E3 & E4) | (E1 & E2 & E3 & ~E4) | (E1 & E2 & E3 & E4);

assign B = (~E1 & E2 & ~E3 & ~E4) | (~E1 & E2 & ~E3 & E4) | (~E1 & E2 & E3 & ~E4) | (~E1 & E2 & E3 & E4) |
           (E1 & ~E2 & ~E3 & ~E4) | (E1 & ~E2 & ~E3 & E4) | (E1 & ~E2 & E3 & ~E4) | (E1 & ~E2 & E3 & E4);

assign C = (~E1 & ~E2 & E3 & ~E4) | (~E1 & ~E2 & E3 & E4) | (~E1 & E2 & ~E3 & ~E4) | (~E1 & E2 & ~E3 & E4) |
           (E1 & ~E2 & E3 & ~E4) | (E1 & ~E2 & E3 & E4) | (E1 & E2 & ~E3 & ~E4) | (E1 & E2 & ~E3 & E4);

assign D = (~E1 & ~E2 & ~E3 & E4) | (~E1 & ~E2 & E3 & ~E4) | (~E1 & E2 & ~E3 & E4) | (~E1 & E2 & E3 & ~E4) |
           (E1 & ~E2 & ~E3 & E4) | (E1 & ~E2 & E3 & ~E4) | (E1 & E2 & ~E3 & E4) | (E1 & E2 & E3 & ~E4);

endmodule

circuitos-combinacionales/eje4/eje4_a.v
module eje4_a (
    input [3:0] bin,
    output reg [3:0] bcd
);

always @(*) begin

    if (bin <= 4'd9)
        bcd = bin;
    else
        bcd = 4'bxxxx;
end


endmodule

circuitos-combinacionales/eje4/eje4_tb.v
`timescale 1ns/1ps

module eje4_tb();

// Entradas eje4_a
reg [3:0] bin;
// Salidas eje4_a
wire [3:0] bcd;

// Instancia del módulo a probar eje4_a
eje4_a UUT(
    .bin(bin),
    .bcd(bcd)
);

// Entradas eje4_b
reg E1;
reg E2;
reg E3;
reg E4;

// Salidas eje4_b
wire A;
wire B;
wire C;
wire D;

// Instancia del módulo a probar eje4_b
eje4_b UUT_b(
    .E1(E1),
    .E2(E2),
    .E3(E3),
    .E4(E4),
    .A(A),
    .B(B),
    .C(C),
    .D(D)
);


// Entradas eje4_b_2
reg [3:0] BN;
// Salidas eje4_b_2
wire [3:0] G;
// Instancia del módulo a probar eje4_b_2
eje4_b_2 UUT_b_2(
    .BN(BN),
    .G(G)
);

// Entradas eje4_c
reg [3:0] bits;
// Salidas eje4_c
wire [6:0] Cod_Hamming;
// Instancia del módulo a probar eje4_c
eje4_c UUT_c(
    .bits(bits),
    .Cod_Hamming(Cod_Hamming)
);



// Variable para iterar en el bucle
integer i;

initial begin
  $dumpfile("eje4_tb.vcd");
  $dumpvars(0, eje4_tb);
  /*
  // Test cases eje4_a
     bin = 4'b0000; // 0
  #1 bin = 4'b0001; // 1
  #1 bin = 4'b0010; // 2
  #1 bin = 4'b0011; // 3
  #1 bin = 4'b0100; // 4
  #1 bin = 4'b0101; // 5
  #1 bin = 4'b0110; // 6
  #1 bin = 4'b0111; // 7
  #1 bin = 4'b1000; // 8
  #1 bin = 4'b1001; // 9
  #1 bin = 4'b1010; // 10 (invalid)
  #1 bin = 4'b1011; // 11 (invalid)
  #1 bin = 4'b1100; // 12 (invalid)
  #1 bin = 4'b1101; // 13 (invalid)
  #1 bin = 4'b1110; // 14 (invalid)
  #1 bin = 4'b1111; // 15 (invalid)
  */

  /*
  // Test cases eje4_b
  {E1, E2, E3, E4} = 4'b0000; // 0
  #1 {E1, E2, E3, E4} = 4'b0001; // 1
  #1 {E1, E2, E3, E4} = 4'b0010; // 2
  #1 {E1, E2, E3, E4} = 4'b0011; // 3
  #1 {E1, E2, E3, E4} = 4'b0100; // 4
  #1 {E1, E2, E3, E4} = 4'b0101; // 5
  #1 {E1, E2, E3, E4} = 4'b0110; // 6
  #1 {E1, E2, E3, E4} = 4'b0111; // 7
  #1 {E1, E2, E3, E4} = 4'b1000; // 8
  #1 {E1, E2, E3, E4} = 4'b1001; // 9
  #1 {E1, E2, E3, E4} = 4'b1010; // 10
  #1 {E1, E2, E3, E4} = 4'b1011; // 11
  #1 {E1, E2, E3, E4} = 4'b1100; // 12
  #1 {E1, E2, E3, E4} = 4'b1101; // 13
  #1 {E1, E2, E3, E4} = 4'b1110; // 14
  #1 {E1, E2, E3, E4} = 4'b1111; // 15
  */
  /*
  // Test cases eje4_b_2
  for(i = 0; i <= 15; i = i + 1) begin
    
    BN = i; // Asignar el valor de i a BN
    #1;
  end
  */

  // Test cases eje4_c
  for(i = 0; i <= 15; i = i + 1) begin
    bits = i; // Asignar el valor de i a bits
    #1;
  end

  $finish;
end

endmodule

circuitos-combinacionales/eje4/eje4_tb.vcd
$date
	Sat May 31 00:36:42 2025
$end
$version
	Icarus Verilog
$end
$timescale
	1ps
$end
$scope module eje4_tb $end
$var wire 4 ! bcd [3:0] $end
$var wire 4 " G [3:0] $end
$var wire 1 # D $end
$var wire 7 $ Cod_Hamming [6:0] $end
$var wire 1 % C $end
$var wire 1 & B $end
$var wire 1 ' A $end
$var reg 4 ( BN [3:0] $end
$var reg 1 ) E1 $end
$var reg 1 * E2 $end
$var reg 1 + E3 $end
$var reg 1 , E4 $end
$var reg 4 - bin [3:0] $end
$var reg 4 . bits [3:0] $end
$var integer 32 / i [31:0] $end
$scope module UUT $end
$var wire 4 0 bin [3:0] $end
$var reg 4 1 bcd [3:0] $end
$upscope $end
$scope module UUT_b $end
$var wire 1 ' A $end
$var wire 1 & B $end
$var wire 1 % C $end
$var wire 1 # D $end
$var wire 1 ) E1 $end
$var wire 1 * E2 $end
$var wire 1 + E3 $end
$var wire 1 , E4 $end
$upscope $end
$scope module UUT_b_2 $end
$var wire 4 2 BN [3:0] $end
$var reg 4 3 G [3:0] $end
$upscope $end
$scope module UUT_c $end
$var wire 4 4 bits [3:0] $end
$var wire 1 5 p1 $end
$var wire 1 6 p2 $end
$var wire 1 7 p3 $end
$var reg 7 8 Cod_Hamming [6:0] $end
$upscope $end
$upscope $end
$enddefinitions $end
$comment Show the parameter values. $end
$dumpall
$end
#0
$dumpvars
b0 8
07
06
05
b0 4
bx 3
bx 2
bx 1
bx 0
b0 /
b0 .
bx -
x,
x+
x*
x)
bx (
x'
x&
x%
b0 $
x#
bx "
bx !
$end
#1000
15
16
17
b1101001 $
b1101001 8
b1 .
b1 4
b1 /
#2000
05
16
17
b101010 $
b101010 8
b10 .
b10 4
b10 /
#3000
15
06
07
b1000011 $
b1000011 8
b11 .
b11 4
b11 /
#4000
15
06
17
b1001100 $
b1001100 8
b100 .
b100 4
b100 /
#5000
05
16
07
b100101 $
b100101 8
b101 .
b101 4
b101 /
#6000
15
16
07
b1100110 $
b1100110 8
b110 .
b110 4
b110 /
#7000
05
06
17
b1111 $
b1111 8
b111 .
b111 4
b111 /
#8000
15
16
07
b1110000 $
b1110000 8
b1000 .
b1000 4
b1000 /
#9000
05
06
17
b11001 $
b11001 8
b1001 .
b1001 4
b1001 /
#10000
15
06
17
b1011010 $
b1011010 8
b1010 .
b1010 4
b1010 /
#11000
05
16
07
b110011 $
b110011 8
b1011 .
b1011 4
b1011 /
#12000
05
16
17
b111100 $
b111100 8
b1100 .
b1100 4
b1100 /
#13000
15
06
07
b1010101 $
b1010101 8
b1101 .
b1101 4
b1101 /
#14000
05
06
07
b10110 $
b10110 8
b1110 .
b1110 4
b1110 /
#15000
15
16
17
b1111111 $
b1111111 8
b1111 .
b1111 4
b1111 /
#16000
b10000 /
