circuitos-secuenciales/eje4/eje4.v
// Flip-Flop D con set y reset asíncronos

module eje4 (
    input wire clk,      
    input wire d,        
    input wire reset,    
    input wire set,    
    output reg q = 0     
);


always @(posedge clk or posedge reset or posedge set) begin
    if (reset)          
        q <= 0;          
    else if (set)     
        q <= 1;          
    else
        q <= d;          
end

endmodule

circuitos-secuenciales/eje4/eje4_tb.v
`timescale 1ns/1ps

module eje4_tb();

// Entradas
reg clk;
reg d;
reg reset;
reg set;
// Salidas
wire q;
eje4 UUT(
    .clk(clk),
    .d(d),
    .reset(reset),
    .set(set),
    .q(q)
);



initial begin
  $dumpfile("eje4_tb.vcd");
  $dumpvars(0, eje4_tb);
  set = 0; // Inicializar set
  reset = 0; // Inicializar reset
  d = 0;
  clk = 0;
  #5;
  d = 1;
  #5;
  clk = 1;
  #3;
  d = 0;
  #1;
  clk = 0;
  #5;
  reset = 1; // Activar reset
  #5;
  reset = 0; // Desactivar reset
  #5;
  set = 1; // Activar set
  #5;
  set = 0; // Desactivar set
  #5;
  clk = 1; // Cambiar el reloj
  #5;
  clk = 0; // Cambiar el reloj
  #2;
  d = 1; // Cambiar la entrada d
  #3;
  clk = 1; // Cambiar el reloj
  #5;
  reset = 1; // Activar reset nuevamente
  set = 1;
  #5;
  reset = 0; // Desactivar reset
  #10;
  $finish;
end

endmodule

circuitos-secuenciales/eje4/eje4_tb.vcd
$date
	Fri Jun 13 21:00:54 2025
$end
$version
	Icarus Verilog
$end
$timescale
	1ps
$end
$scope module eje4_tb $end
$var wire 1 ! q $end
$var reg 1 " clk $end
$var reg 1 # d $end
$var reg 1 $ reset $end
$var reg 1 % set $end
$scope module UUT $end
$var wire 1 " clk $end
$var wire 1 # d $end
$var wire 1 $ reset $end
$var wire 1 % set $end
$var reg 1 ! q $end
$upscope $end
$upscope $end
$enddefinitions $end
$comment Show the parameter values. $end
$dumpall
$end
#0
$dumpvars
0%
0$
0#
0"
0!
$end
#5000
1#
#10000
1!
1"
#13000
0#
#14000
0"
#19000
0!
1$
#24000
0$
#29000
1!
1%
#34000
0%
#39000
0!
1"
#44000
0"
#46000
1#
#49000
1!
1"
#54000
0!
1%
1$
#59000
0$
