circuitos-secuenciales/eje2/eje2.v
/// Flip-Flop D

module eje2 (
    input wire clk,     // Reloj
    input wire d,       // Entrada d
    output reg q = 0       // Salida
);

    always @(posedge clk) begin
        q <= d; // Asignación de la entrada d a la salida q en el flanco ascendente del reloj
    end

endmodule

circuitos-secuenciales/eje2/eje2_tb.v
`timescale 1ns/1ps

module eje2_tb();

// Entradas
  reg s_clk;
  reg s_d;

// Salida
  wire s_q;

eje2 UUT(
    .clk(s_clk),
    .d(s_d),
    .q(s_q)
);

// Generador de reloj: periodo de 10 ns
always #5 s_clk = ~s_clk;

initial begin
  $dumpfile("eje2_tb.vcd");
  $dumpvars(0, eje2_tb);
  
  s_clk = 0;
  s_d = 0;

  // Secuencia de prueba
  #12 s_d = 1;   // Cambia a 1 antes del siguiente flanco
  #10 s_d = 0;   // Cambia a 0 después de un ciclo
  #10 s_d = 1;   // Cambia a 1 después de otro ciclo
  #10 s_d = 0;   // Cambia a 0 después de otro ciclo

  $finish;
end

endmodule

circuitos-secuenciales/eje2/eje2_tb.vcd
$date
	Mon May 26 10:43:56 2025
$end
$version
	Icarus Verilog
$end
$timescale
	1ps
$end
$scope module eje2_tb $end
$var wire 1 ! s_q $end
$var reg 1 " s_clk $end
$var reg 1 # s_d $end
$scope module UUT $end
$var wire 1 " clk $end
$var wire 1 # d $end
$var reg 1 ! q $end
$upscope $end
$upscope $end
$enddefinitions $end
$comment Show the parameter values. $end
$dumpall
$end
#0
$dumpvars
0#
0"
0!
$end
#5000
1"
#10000
0"
#12000
1#
#15000
1!
1"
#20000
0"
#22000
0#
#25000
0!
1"
#30000
0"
#32000
1#
#35000
1!
1"
#40000
0"
#42000
0#
