maquinas-estados-finitos/eje9/flip_flop_d.v
/// Flip-Flop D


module flip_flop_d(
    input clk,
    input d,
    output reg q = 0
);

always @(posedge clk) begin
    q = d;
end

endmodule

maquinas-estados-finitos/eje9/eje9.v
module eje9(
  input w,
  input clk,
  output q1,
  output q0,
  output z_s
);

assign z_s = q1 & q0;

wire d1, d0;

assign d1 = (w & q0) | (q1 & ~q0);
assign d0 = (q1 & ~q0) | (q1 & w) | (w & ~q0);

flip_flop_d FFD_1(
  .clk(clk),
  .d(d1),
  .q(q1)
);
flip_flop_d FFD_2(
  .clk(clk),
  .d(d0),
  .q(q0)
);

endmodule

maquinas-estados-finitos/eje9/eje9_tb.v
`timescale 1ns/1ps

module eje9_tb();

// Entradas
reg w;
reg clk;
// Salidas
wire q1;
wire q0;
wire z_s;

eje9 UUT(
  .w(w),
  .clk(clk),
  .q1(q1),
  .q0(q0),
  .z_s(z_s)
);



initial begin
  $dumpfile("eje9_tb.vcd");
  $dumpvars(0, eje9_tb);
  clk = 0;
  w = 0; 
  #10;
  w = 1;
  #5;
  clk = 1;
  #5;
  w = 0;
  #5;
  clk = 0;
  #5;
  w = 1;
  #5;
  clk = 1;
  #5;
  w = 0;
  #5;
  clk = 0;
  #5;
  clk = 1;
  #5;
  clk = 0;
  #10;

  $finish;
end

endmodule

maquinas-estados-finitos/eje9/eje9_tb.vcd
$date
	Mon Jun 16 14:48:41 2025
$end
$version
	Icarus Verilog
$end
$timescale
	1ps
$end
$scope module eje9_tb $end
$var wire 1 ! z_s $end
$var wire 1 " q1 $end
$var wire 1 # q0 $end
$var reg 1 $ clk $end
$var reg 1 % w $end
$scope module UUT $end
$var wire 1 $ clk $end
$var wire 1 & d0 $end
$var wire 1 ' d1 $end
$var wire 1 % w $end
$var wire 1 ! z_s $end
$var wire 1 " q1 $end
$var wire 1 # q0 $end
$scope module FFD_1 $end
$var wire 1 $ clk $end
$var wire 1 ' d $end
$var reg 1 " q $end
$upscope $end
$scope module FFD_2 $end
$var wire 1 $ clk $end
$var wire 1 & d $end
$var reg 1 # q $end
$upscope $end
$upscope $end
$upscope $end
$enddefinitions $end
$comment Show the parameter values. $end
$dumpall
$end
#0
$dumpvars
0'
0&
0%
0$
0#
0"
0!
$end
#10000
1&
1%
#15000
0&
1'
1#
1$
#20000
0'
0%
#25000
0$
#30000
1'
1%
#35000
1&
1'
0#
1"
1$
#40000
0%
#45000
0$
#50000
0&
0'
1!
1#
1$
