circuitos-aritmeticos-logicos/eje5/eje5.v
module eje5(
    input [3:0] datos,
    input [2:0] op,
    output reg[3:0] datosMod
);

always @(*)begin

    case(op) 
    3'b000: datosMod = datos;
    3'b001: datosMod = {1'b0, datos[3], datos[2], datos[1]};
    3'b010: datosMod = {datos[2], datos[1], datos[0], 1'b0};
    3'b101: datosMod = {datos[3], datos[3], datos[2], datos[1]};
    3'b110: datosMod = {datos[2], datos[1], datos[0], 1'b0};
    3'b011: datosMod = {datos[0], datos[3], datos[2], datos[1]};
    3'b111: datosMod = {datos[2], datos[1], datos[0], datos[3]};
    default: datosMod = 4'b0000;
    endcase

end


endmodule



































/*module eje5(
    input [3:0] A,
    input [2:0] op,
    output reg[3:0] X

);
always @(*) begin
    case (op)
        3'b000: X = A;
        3'b001: begin
            X[3] = 0; 
            X[2] = A[3]; 
            X[1] = A[2]; 
            X[0] = A[1];
        end
        3'b010: begin
             X[3] = A[2];
             X[2] = A[1]; 
             X[1] = A[0]; 
             X[0] = 0; 
        end
        3'b101: begin
            X[3] = A[3];
            X[2] = A[3];
            X[1] = A[2];
            X[0] = A[1];
        end
        3'b110: begin
            X[3] = A[2];
            X[2] = A[1];
            X[1] = A[0];
            X[0] = 0; 
        end
        3'b011: begin
            X[3] = A[0];
            X[2] = A[3];
            X[1] = A[2];
            X[0] = A[1]; 
        end
        3'b111: begin
            X[3] = A[2];
            X[2] = A[1];
            X[1] = A[0];
            X[0] = A[3]; 
        end 
        default: X = 4'b0000;
    endcase
end


endmodule
*/

circuitos-aritmeticos-logicos/eje5/eje5_tb.v
`timescale 1ns/1ps


module eje5_tb();

reg [3:0] A;
reg [2:0] op;
wire [3:0] datosMod;

eje5 UUT(
    .datos(A),
    .op(op),
    .datosMod(datosMod)
);


initial begin
    $dumpfile("eje5_tb.vcd");
    $dumpvars(0, eje5_tb);
    A = 4'b0111;
    op = 3'b000;
    #10;
    op = 3'b001;
    #10;
    op = 3'b010;
    #10;
    op = 3'b101;
    #10;
    op = 3'b110;
    #10;
    op = 3'b011;
    #10;
    op = 3'b111;
    #10;
    op = 3'b100;
    #10;
    
    $finish;
end

endmodule

circuitos-aritmeticos-logicos/eje5/eje5_tb.vcd
$date
	Thu Jun 12 19:29:39 2025
$end
$version
	Icarus Verilog
$end
$timescale
	1ps
$end
$scope module eje5_tb $end
$var wire 4 ! datosMod [3:0] $end
$var reg 4 " A [3:0] $end
$var reg 3 # op [2:0] $end
$scope module UUT $end
$var wire 4 $ datos [3:0] $end
$var wire 3 % op [2:0] $end
$var reg 4 & datosMod [3:0] $end
$upscope $end
$upscope $end
$enddefinitions $end
$comment Show the parameter values. $end
$dumpall
$end
#0
$dumpvars
b111 &
b0 %
b111 $
b0 #
b111 "
b111 !
$end
#10000
b11 !
b11 &
b1 #
b1 %
#20000
b1110 !
b1110 &
b10 #
b10 %
#30000
b11 !
b11 &
b101 #
b101 %
#40000
b1110 !
b1110 &
b110 #
b110 %
#50000
b1011 !
b1011 &
b11 #
b11 %
#60000
b1110 !
b1110 &
b111 #
b111 %
#70000
b0 !
b0 &
b100 #
b100 %
