circuitos-secuenciales/eje2/eje2.v
/// Flip-Flop JK

/// Flip-Flop JK básico

module eje1 (
    input wire clk,     // Reloj
    input wire j,       // Entrada J
    input wire k,       // Entrada K
    output reg q = 0       // Salida
);

    always @(posedge clk) begin
        case ({j, k})
            2'b00: q <= q;       // Mantiene el estado
            2'b01: q <= 0;       // Reset
            2'b10: q <= 1;       // Set
            2'b11: q <= ~q;      // Toggle
        endcase
    end

endmodule

circuitos-secuenciales/eje1/eje1_tb.v
`timescale 1ns/1ps

module eje1_tb();

// Entradas
  reg s_clk;
  reg s_j;
  reg s_k;

// Salida
  wire s_q;

eje1 UUT(
    .clk(s_clk),
    .j(s_j),
    .k(s_k),
    .q(s_q)
);

// Generador de reloj: periodo de 10 ns
always #5 s_clk = ~s_clk;

initial begin
  $dumpfile("eje1_tb.vcd");
  $dumpvars(0, eje1_tb);
  
  s_clk = 0;
  s_j = 0;
  s_k = 0;

  // Secuencia de prueba
  #10 s_j = 1; s_k = 0; // Set
  #10 s_j = 0; s_k = 1; // Reset
  #10 s_j = 1; s_k = 1; // Toggle
  #10 s_j = 0; s_k = 0; // Mantener
  #10 s_j = 1; s_k = 1; // Toggle
  #10 s_j = 0; s_k = 1; // Reset
  #10 s_j = 1; s_k = 0; // Set

  $finish;
end

endmodule

circuitos-secuenciales/eje1/eje1_tb.vcd
$date
	Mon May 26 10:18:06 2025
$end
$version
	Icarus Verilog
$end
$timescale
	1ps
$end
$scope module eje1_tb $end
$var wire 1 ! s_q $end
$var reg 1 " s_clk $end
$var reg 1 # s_j $end
$var reg 1 $ s_k $end
$scope module UUT $end
$var wire 1 " clk $end
$var wire 1 # j $end
$var wire 1 $ k $end
$var reg 1 ! q $end
$upscope $end
$upscope $end
$enddefinitions $end
$comment Show the parameter values. $end
$dumpall
$end
#0
$dumpvars
0$
0#
0"
1!
$end
#5000
1"
#10000
0"
1#
#15000
1"
#20000
0"
1$
0#
#25000
0!
1"
#30000
0"
1#
#35000
1!
1"
#40000
0"
0$
0#
#45000
1"
#50000
0"
1$
1#
#55000
0!
1"
#60000
0"
0#
#65000
1"
#70000
0"
0$
1#
