circuitos-aritmeticos-logicos/eje6/alu_4b.v
module alu_4b(
    input [3:0] A,
    input [3:0] B,
    input [3:0] op,
    output reg [3:0] result
);


always @(*) begin
    case (op)
        4'b0001: result = A & B;
        4'b0010: result = A | B;
        4'b0011: result = A ^ B;
        4'b0101: result = A + B;
        4'b0110: result = A - B;
        4'b1001: result = (A < B) ? 4'b0001 : 4'b0000;
        4'b1010: result = (A == B) ? 4'b0001 : 4'b0000;
        4'b1101: result = A >> 1;
        4'b1110: result = A << 1;
        default: result = 4'b0000;
    endcase
end


endmodule

circuitos-aritmeticos-logicos/eje6/alu_4b_tb.v
`timescale 1ns/1ps

module alu_4b_tb();

reg [3:0] A;
reg [3:0] B;
reg [3:0] op;
wire [3:0] result;


alu_4b UUT(
    .A(A),
    .B(B),
    .op(op),
    .result(result)
);

initial begin
    $dumpfile("alu_4b_tb.vcd");
    $dumpvars(0, alu_4b_tb);
    $display("Time\tOp\tA\tB\tResult");

    // Prueba para cada operación
        
        // Operación: AND
        A = 4'b1010; B = 4'b1100; op = 4'b0001; // Espera: 1000
        #10;
        $display("%0t\t%4b\t%4b\t%4b\t%4b",$time, op, A, B, result);
        
        // Operación: OR
        A = 4'b1010; B = 4'b1100; op = 4'b0010; // Espera: 1110
        #10;
        $display("%0t\t%4b\t%4b\t%4b\t%4b",$time, op, A, B, result);
        
        // Operación: XOR
        A = 4'b1010; B = 4'b1100; op = 4'b0011; // Espera: 0110
        #10;
        $display("%0t\t%4b\t%4b\t%4b\t%4b",$time, op, A, B, result);
        
        // Operación: Suma
        A = 4'b0101; B = 4'b0011; op = 4'b0101; // Espera: 0110
        #10;
        $display("%0t\t%4b\t%4b\t%4b\t%4b",$time, op, A, B, result);
        
        // Operación: Resta
        A = 4'b1001; B = 4'b0010; op = 4'b0110; // Espera: 0111 (9-2=7)
        #10;
        $display("%0t\t%4b\t%4b\t%4b\t%4b",$time, op, A, B, result);
        
        // Operación: Comparación (A<B)
        A = 4'b0011; B = 4'b1010; op = 4'b1001; // Espera: 0001 (true)
        #10;
        $display("%0t\t%4b\t%4b\t%4b\t%4b",$time, op, A, B, result);
        
        A = 4'b1010; B = 4'b0011; op = 4'b1001; // Espera: 0000 (false)
        #10;
        $display("%0t\t%4b\t%4b\t%4b\t%4b",$time, op, A, B, result);
        
        // Operación: Comparación (A==B)
        A = 4'b1111; B = 4'b1111; op = 4'b1010; // Espera: 0001 (true)
        #10;
        $display("%0t\t%4b\t%4b\t%4b\t%4b",$time, op, A, B, result);
        
        A = 4'b1010; B = 4'b1111; op = 4'b1010; // Espera: 0000 (false)
        #10;
        $display("%0t\t%4b\t%4b\t%4b\t%4b",$time, op, A, B, result);
        
        // Operación: Desplazar a la derecha
        A = 4'b1010; op = 4'b1101; // Espera: 0101 (se pierde el bit menos significativo)
        #10;
        $display("%0t\t%4b\t%4b\t----\t%4b",$time, op, A, result);
        
        // Operación: Desplazar a la izquierda
        A = 4'b0101; op = 4'b1110; // Espera: 1010 
        #10;
        $display("%0t\t%4b\t%4b\t----\t%4b",$time, op, A, result);
        
        $finish;

end




endmodule

circuitos-aritmeticos-logicos/eje6/dump.vcd
$date
	Mon May 12 09:37:55 2025
$end
$version
	Icarus Verilog
$end
$timescale
	1ps
$end
$scope module alu_4b_tb $end
$var wire 4 ! result [3:0] $end
$var reg 4 " A [3:0] $end
$var reg 4 # B [3:0] $end
$var reg 4 $ op [3:0] $end
$scope module UUT $end
$var wire 4 % A [3:0] $end
$var wire 4 & B [3:0] $end
$var wire 4 ' op [3:0] $end
$var reg 4 ( result [3:0] $end
$upscope $end
$upscope $end
$enddefinitions $end
$comment Show the parameter values. $end
$dumpall
$end
#0
$dumpvars
b1000 (
b1 '
b1100 &
b1010 %
b1 $
b1100 #
b1010 "
b1000 !
$end
#10000
b1110 !
b1110 (
b10 $
b10 '
#20000
b110 !
b110 (
b11 $
b11 '
#30000
b1000 !
b1000 (
b101 $
b101 '
b11 #
b11 &
b101 "
b101 %
#40000
b111 !
b111 (
b110 $
b110 '
b10 #
b10 &
b1001 "
b1001 %
#50000
b1 !
b1 (
b1001 $
b1001 '
b1010 #
b1010 &
b11 "
b11 %
#60000
b0 !
b0 (
b11 #
b11 &
b1010 "
b1010 %
#70000
b1 !
b1 (
b1010 $
b1010 '
b1111 #
b1111 &
b1111 "
b1111 %
#80000
b0 !
b0 (
b1010 "
b1010 %
#90000
b101 !
b101 (
b1101 $
b1101 '
#100000
b1010 !
b1010 (
b1110 $
b1110 '
b101 "
b101 %
